{"response": {"plots": [{"height": 45, "url": "https://plot.ly/~jim.robinson/3775.embed?link=false&modebar=false"}, {"height": 70, "url": "https://plot.ly/~jim.robinson/3767"}, {"height": 295, "url": "https://plot.ly/~jim.robinson/3769"}, {"height": 95, "url": "https://plot.ly/~jim.robinson/3771"}, {"height": 45, "url": "https://plot.ly/~jim.robinson/3773"}]}, "request": {"ts_gte": 1466679600, "operators": "All Operators", "timeline_set": [{"name": "All Machines", "type": "group", "desc": "All Machines", "id": "<some_id>"}], "next_link": "/some/link", "timezone": "US/Eastern", "prev_link": "/some/link", "ts_lt": 1467284400, "time_desc": "First Fully Installed Week"}}